Metadata-Version: 2.1
Name: ssurgo-aggregation
Version: 0.0.1
Summary: This is a python package to aggregate the Natural Resources Conservation Service (NRCS) Soil Survey Geographic Database.
Home-page: https://github.com/Geobalies2019/ssurgo_aggregation
Author: Abiodun Ayo-Bali
Author-email: ayobali.biodun@gmail.com
License: MIT license
Keywords: ssurgo_aggregation
Classifier: Intended Audience :: Developers
Classifier: License :: OSI Approved :: MIT License
Classifier: Natural Language :: English
Classifier: Programming Language :: Python :: 3
Classifier: Programming Language :: Python :: 3.8
Classifier: Programming Language :: Python :: 3.9
Classifier: Programming Language :: Python :: 3.10
Classifier: Programming Language :: Python :: 3.11
Requires-Python: >=3.8
License-File: LICENSE
